MANIFEST.in
README.rst
setup.py
chatproj/__init__.py
chatproj/settings.py
chatproj/urls.py
chatproj/wsgi.py
otreechat/__init__.py
otreechat/consumers.py
otreechat/models.py
otreechat/views.py
otreechat.egg-info/PKG-INFO
otreechat.egg-info/SOURCES.txt
otreechat.egg-info/dependency_links.txt
otreechat.egg-info/top_level.txt
otreechat/otree_extensions/__init__.py
otreechat/otree_extensions/admin.py
otreechat/otree_extensions/routing.py
otreechat/templates/otreechat/widget.html
otreechat/templatetags/__init__.py
otreechat/templatetags/otreechat.py